{
	"description": "项目配置文件。",
	"setting": {
		"urlCheck": true,
		"es6": true,
		"postcss": true,
		"minified": true,
		"newFeature": true
	},
	"compileType": "miniprogram",
	"libVersion": "1.9.91",
	"appid": "wx8342f1219d44ba32",
	"projectname": "wlog",
	"isGameTourist": false,
	"condition": {
		"search": {
			"current": -1,
			"list": []
		},
		"conversation": {
			"current": -1,
			"list": []
		},
		"game": {
			"currentL": -1,
			"list": []
		},
		"miniprogram": {
			"current": 0,
			"list": [
				{
					"id": -1,
					"name": "habits",
					"pathName": "pages/habits",
					"query": ""
				},
				{
					"id": -1,
					"name": "habit",
					"pathName": "pages/habit",
					"query": ""
				},
				{
					"id": -1,
					"name": "stats",
					"pathName": "pages/stats",
					"query": ""
				}
			]
		}
	}
}